corpus_distance/__init__.py
corpus_distance/cdutils.py
corpus_distance/pipeline.py
corpus_distance/clusterisation/__init__.py
corpus_distance/clusterisation/clusterisation.py
corpus_distance/clusterisation/utils.py
corpus_distance/data/__init__.py
corpus_distance/data/config.json
corpus_distance/data/data_resources.py
corpus_distance/data/gospels.csv
corpus_distance/data_preprocessing/__init__.py
corpus_distance/data_preprocessing/data_loading.py
corpus_distance/data_preprocessing/data_pipeline.py
corpus_distance/data_preprocessing/frequency_scoring.py
corpus_distance/data_preprocessing/shingle_processing.py
corpus_distance/data_preprocessing/topic_modelling.py
corpus_distance/data_preprocessing/vectorisation.py
corpus_distance/distance_measurement/__init__.py
corpus_distance/distance_measurement/analysis.py
corpus_distance/distance_measurement/frequency_metrics.py
corpus_distance/distance_measurement/hybridisation.py
corpus_distance/distance_measurement/metrics_pipeline.py
corpus_distance/distance_measurement/string_similarity.py
corpus_distance-0.6.7.dist-info/licenses/LICENSE
corpus_distance-0.6.7.dist-info/METADATA
corpus_distance-0.6.7.dist-info/WHEEL
corpus_distance-0.6.7.dist-info/top_level.txt
corpus_distance-0.6.7.dist-info/RECORD
