Metadata-Version: 2.4
Name: corpus_distance
Version: 0.6.7
Summary: Python package for measuring distance between the lects represented by small raw corpora
Author-email: Ilia Afanasev <ilia.afanasev.1997@gmail.com>
Project-URL: Homepage, https://github.com/The-One-Who-Speaks-and-Depicts/corpus_distance
Project-URL: Issues, https://github.com/The-One-Who-Speaks-and-Depicts/corpus_distance/issues
Classifier: Programming Language :: Python :: 3
Classifier: License :: OSI Approved :: Mozilla Public License 2.0 (MPL 2.0)
Classifier: Operating System :: OS Independent
Requires-Python: >=3.10.12
License-File: LICENSE
Requires-Dist: setuptools>=67.7.2
Requires-Dist: biopython==1.83
Requires-Dist: gensim==4.3.2
Requires-Dist: Levenshtein==0.25.0
Requires-Dist: matplotlib==3.7.1
Requires-Dist: numpy==1.26.0
Requires-Dist: pandas==2.1.1
Requires-Dist: pyjarowinkler==1.8
Requires-Dist: scipy==1.11.4
Requires-Dist: tqdm==4.66.4
Requires-Dist: packaging==21.3
Dynamic: license-file
